{"nodes": [{"id": "d_transplant518test_sglang518_sgl_model_gateway_src_core_steps_worker_local_find_worker_to_update_rs", "label": "find_worker_to_update.rs", "file_type": "code", "source_file": "D:\\transplant518test\\sglang518\\sgl-model-gateway\\src\\core\\steps\\worker\\local\\find_worker_to_update.rs", "source_location": "L1"}, {"id": "local_find_worker_to_update_findworkertoupdatestep", "label": "FindWorkerToUpdateStep", "file_type": "code", "source_file": "D:\\transplant518test\\sglang518\\sgl-model-gateway\\src\\core\\steps\\worker\\local\\find_worker_to_update.rs", "source_location": "L14"}, {"id": "local_find_worker_to_update_findworkertoupdatestep_execute", "label": ".execute()", "file_type": "code", "source_file": "D:\\transplant518test\\sglang518\\sgl-model-gateway\\src\\core\\steps\\worker\\local\\find_worker_to_update.rs", "source_location": "L18"}, {"id": "local_find_worker_to_update_findworkertoupdatestep_is_retryable", "label": ".is_retryable()", "file_type": "code", "source_file": "D:\\transplant518test\\sglang518\\sgl-model-gateway\\src\\core\\steps\\worker\\local\\find_worker_to_update.rs", "source_location": "L56"}], "edges": [{"source": "d_transplant518test_sglang518_sgl_model_gateway_src_core_steps_worker_local_find_worker_to_update_rs", "target": "async_trait", "relation": "imports_from", "confidence": "EXTRACTED", "source_file": "D:\\transplant518test\\sglang518\\sgl-model-gateway\\src\\core\\steps\\worker\\local\\find_worker_to_update.rs", "source_location": "L3", "weight": 1.0, "context": "import"}, {"source": "d_transplant518test_sglang518_sgl_model_gateway_src_core_steps_worker_local_find_worker_to_update_rs", "target": "debug", "relation": "imports_from", "confidence": "EXTRACTED", "source_file": "D:\\transplant518test\\sglang518\\sgl-model-gateway\\src\\core\\steps\\worker\\local\\find_worker_to_update.rs", "source_location": "L4", "weight": 1.0, "context": "import"}, {"source": "d_transplant518test_sglang518_sgl_model_gateway_src_core_steps_worker_local_find_worker_to_update_rs", "target": "wfaas", "relation": "imports_from", "confidence": "EXTRACTED", "source_file": "D:\\transplant518test\\sglang518\\sgl-model-gateway\\src\\core\\steps\\worker\\local\\find_worker_to_update.rs", "source_location": "L5", "weight": 1.0, "context": "import"}, {"source": "d_transplant518test_sglang518_sgl_model_gateway_src_core_steps_worker_local_find_worker_to_update_rs", "target": "find_workers_by_url", "relation": "imports_from", "confidence": "EXTRACTED", "source_file": "D:\\transplant518test\\sglang518\\sgl-model-gateway\\src\\core\\steps\\worker\\local\\find_worker_to_update.rs", "source_location": "L7", "weight": 1.0, "context": "import"}, {"source": "d_transplant518test_sglang518_sgl_model_gateway_src_core_steps_worker_local_find_worker_to_update_rs", "target": "workerupdateworkflowdata", "relation": "imports_from", "confidence": "EXTRACTED", "source_file": "D:\\transplant518test\\sglang518\\sgl-model-gateway\\src\\core\\steps\\worker\\local\\find_worker_to_update.rs", "source_location": "L8", "weight": 1.0, "context": "import"}, {"source": "d_transplant518test_sglang518_sgl_model_gateway_src_core_steps_worker_local_find_worker_to_update_rs", "target": "local_find_worker_to_update_findworkertoupdatestep", "relation": "contains", "confidence": "EXTRACTED", "source_file": "D:\\transplant518test\\sglang518\\sgl-model-gateway\\src\\core\\steps\\worker\\local\\find_worker_to_update.rs", "source_location": "L14", "weight": 1.0}, {"source": "local_find_worker_to_update_findworkertoupdatestep", "target": "local_find_worker_to_update_findworkertoupdatestep_execute", "relation": "method", "confidence": "EXTRACTED", "source_file": "D:\\transplant518test\\sglang518\\sgl-model-gateway\\src\\core\\steps\\worker\\local\\find_worker_to_update.rs", "source_location": "L18", "weight": 1.0}, {"source": "local_find_worker_to_update_findworkertoupdatestep", "target": "local_find_worker_to_update_findworkertoupdatestep_is_retryable", "relation": "method", "confidence": "EXTRACTED", "source_file": "D:\\transplant518test\\sglang518\\sgl-model-gateway\\src\\core\\steps\\worker\\local\\find_worker_to_update.rs", "source_location": "L56", "weight": 1.0}], "raw_calls": [{"caller_nid": "local_find_worker_to_update_findworkertoupdatestep_execute", "callee": "ok_or_else", "is_member_call": true, "source_file": "D:\\transplant518test\\sglang518\\sgl-model-gateway\\src\\core\\steps\\worker\\local\\find_worker_to_update.rs", "source_location": "L24"}, {"caller_nid": "local_find_worker_to_update_findworkertoupdatestep_execute", "callee": "as_ref", "is_member_call": true, "source_file": "D:\\transplant518test\\sglang518\\sgl-model-gateway\\src\\core\\steps\\worker\\local\\find_worker_to_update.rs", "source_location": "L24"}, {"caller_nid": "local_find_worker_to_update_findworkertoupdatestep_execute", "callee": "ContextValueNotFound", "is_member_call": false, "source_file": "D:\\transplant518test\\sglang518\\sgl-model-gateway\\src\\core\\steps\\worker\\local\\find_worker_to_update.rs", "source_location": "L28"}, {"caller_nid": "local_find_worker_to_update_findworkertoupdatestep_execute", "callee": "to_string", "is_member_call": true, "source_file": "D:\\transplant518test\\sglang518\\sgl-model-gateway\\src\\core\\steps\\worker\\local\\find_worker_to_update.rs", "source_location": "L28"}, {"caller_nid": "local_find_worker_to_update_findworkertoupdatestep_execute", "callee": "find_workers_by_url", "is_member_call": false, "source_file": "D:\\transplant518test\\sglang518\\sgl-model-gateway\\src\\core\\steps\\worker\\local\\find_worker_to_update.rs", "source_location": "L31"}, {"caller_nid": "local_find_worker_to_update_findworkertoupdatestep_execute", "callee": "is_empty", "is_member_call": true, "source_file": "D:\\transplant518test\\sglang518\\sgl-model-gateway\\src\\core\\steps\\worker\\local\\find_worker_to_update.rs", "source_location": "L33"}, {"caller_nid": "local_find_worker_to_update_findworkertoupdatestep_execute", "callee": "Err", "is_member_call": false, "source_file": "D:\\transplant518test\\sglang518\\sgl-model-gateway\\src\\core\\steps\\worker\\local\\find_worker_to_update.rs", "source_location": "L39"}, {"caller_nid": "local_find_worker_to_update_findworkertoupdatestep_execute", "callee": "new", "is_member_call": false, "source_file": "D:\\transplant518test\\sglang518\\sgl-model-gateway\\src\\core\\steps\\worker\\local\\find_worker_to_update.rs", "source_location": "L40"}, {"caller_nid": "local_find_worker_to_update_findworkertoupdatestep_execute", "callee": "Some", "is_member_call": false, "source_file": "D:\\transplant518test\\sglang518\\sgl-model-gateway\\src\\core\\steps\\worker\\local\\find_worker_to_update.rs", "source_location": "L51"}, {"caller_nid": "local_find_worker_to_update_findworkertoupdatestep_execute", "callee": "Ok", "is_member_call": false, "source_file": "D:\\transplant518test\\sglang518\\sgl-model-gateway\\src\\core\\steps\\worker\\local\\find_worker_to_update.rs", "source_location": "L53"}]}