{"nodes": [{"id": "d_transplant518test_sglang518_docs_new_docs_hardware_platforms_ascend_npus_mindspore_backend_mdx", "label": "mindspore_backend.mdx", "file_type": "document", "source_file": "D:\\transplant518test\\sglang518\\docs_new\\docs\\hardware-platforms\\ascend-npus\\mindspore_backend.mdx", "source_location": "L1"}, {"id": "ascend_npus_mindspore_backend_introduction", "label": "Introduction", "file_type": "document", "source_file": "D:\\transplant518test\\sglang518\\docs_new\\docs\\hardware-platforms\\ascend-npus\\mindspore_backend.mdx", "source_location": "L1"}, {"id": "ascend_npus_mindspore_backend_requirements", "label": "Requirements", "file_type": "document", "source_file": "D:\\transplant518test\\sglang518\\docs_new\\docs\\hardware-platforms\\ascend-npus\\mindspore_backend.mdx", "source_location": "L5"}, {"id": "ascend_npus_mindspore_backend_supported_models", "label": "Supported Models", "file_type": "document", "source_file": "D:\\transplant518test\\sglang518\\docs_new\\docs\\hardware-platforms\\ascend-npus\\mindspore_backend.mdx", "source_location": "L10"}, {"id": "ascend_npus_mindspore_backend_installation", "label": "Installation", "file_type": "document", "source_file": "D:\\transplant518test\\sglang518\\docs_new\\docs\\hardware-platforms\\ascend-npus\\mindspore_backend.mdx", "source_location": "L18"}, {"id": "ascend_npus_mindspore_backend_codeblock_1", "label": "code:shell (git clone https://github.com/mindspore-lab/sgl-mindspore.git)", "file_type": "document", "source_file": "D:\\transplant518test\\sglang518\\docs_new\\docs\\hardware-platforms\\ascend-npus\\mindspore_backend.mdx", "source_location": "L25"}, {"id": "ascend_npus_mindspore_backend_run_model", "label": "Run Model", "file_type": "document", "source_file": "D:\\transplant518test\\sglang518\\docs_new\\docs\\hardware-platforms\\ascend-npus\\mindspore_backend.mdx", "source_location": "L33"}, {"id": "ascend_npus_mindspore_backend_offline_infer", "label": "Offline infer", "file_type": "document", "source_file": "D:\\transplant518test\\sglang518\\docs_new\\docs\\hardware-platforms\\ascend-npus\\mindspore_backend.mdx", "source_location": "L37"}, {"id": "ascend_npus_mindspore_backend_codeblock_2", "label": "code:python (import sglang as sgl)", "file_type": "document", "source_file": "D:\\transplant518test\\sglang518\\docs_new\\docs\\hardware-platforms\\ascend-npus\\mindspore_backend.mdx", "source_location": "L42"}, {"id": "ascend_npus_mindspore_backend_start_server", "label": "Start server", "file_type": "document", "source_file": "D:\\transplant518test\\sglang518\\docs_new\\docs\\hardware-platforms\\ascend-npus\\mindspore_backend.mdx", "source_location": "L72"}, {"id": "ascend_npus_mindspore_backend_codeblock_3", "label": "code:bash (# Basic server startup)", "file_type": "document", "source_file": "D:\\transplant518test\\sglang518\\docs_new\\docs\\hardware-platforms\\ascend-npus\\mindspore_backend.mdx", "source_location": "L77"}, {"id": "ascend_npus_mindspore_backend_codeblock_4", "label": "code:bash (# Multi-node distributed server)", "file_type": "document", "source_file": "D:\\transplant518test\\sglang518\\docs_new\\docs\\hardware-platforms\\ascend-npus\\mindspore_backend.mdx", "source_location": "L93"}, {"id": "ascend_npus_mindspore_backend_troubleshooting", "label": "Troubleshooting", "file_type": "document", "source_file": "D:\\transplant518test\\sglang518\\docs_new\\docs\\hardware-platforms\\ascend-npus\\mindspore_backend.mdx", "source_location": "L109"}, {"id": "ascend_npus_mindspore_backend_debug_mode", "label": "Debug Mode", "file_type": "document", "source_file": "D:\\transplant518test\\sglang518\\docs_new\\docs\\hardware-platforms\\ascend-npus\\mindspore_backend.mdx", "source_location": "L111"}, {"id": "ascend_npus_mindspore_backend_codeblock_5", "label": "code:bash (python3 -m sglang.launch_server \\)", "file_type": "document", "source_file": "D:\\transplant518test\\sglang518\\docs_new\\docs\\hardware-platforms\\ascend-npus\\mindspore_backend.mdx", "source_location": "L116"}, {"id": "ascend_npus_mindspore_backend_codeblock_6", "label": "code:bash (export GLOG_v=1  # INFO)", "file_type": "document", "source_file": "D:\\transplant518test\\sglang518\\docs_new\\docs\\hardware-platforms\\ascend-npus\\mindspore_backend.mdx", "source_location": "L130"}, {"id": "ascend_npus_mindspore_backend_explicitly_select_devices", "label": "Explicitly select devices", "file_type": "document", "source_file": "D:\\transplant518test\\sglang518\\docs_new\\docs\\hardware-platforms\\ascend-npus\\mindspore_backend.mdx", "source_location": "L136"}, {"id": "ascend_npus_mindspore_backend_codeblock_7", "label": "code:shell (export ASCEND_RT_VISIBLE_DEVICES=4,5,6,7  # to set device)", "file_type": "document", "source_file": "D:\\transplant518test\\sglang518\\docs_new\\docs\\hardware-platforms\\ascend-npus\\mindspore_backend.mdx", "source_location": "L141"}, {"id": "ascend_npus_mindspore_backend_some_communication_environment_issues", "label": "Some communication environment issues", "file_type": "document", "source_file": "D:\\transplant518test\\sglang518\\docs_new\\docs\\hardware-platforms\\ascend-npus\\mindspore_backend.mdx", "source_location": "L146"}, {"id": "ascend_npus_mindspore_backend_codeblock_8", "label": "code:shell (export MS_ENABLE_LCCL=off # current not support LCCL communi)", "file_type": "document", "source_file": "D:\\transplant518test\\sglang518\\docs_new\\docs\\hardware-platforms\\ascend-npus\\mindspore_backend.mdx", "source_location": "L151"}, {"id": "ascend_npus_mindspore_backend_some_dependencies_of_protobuf", "label": "Some dependencies of protobuf", "file_type": "document", "source_file": "D:\\transplant518test\\sglang518\\docs_new\\docs\\hardware-platforms\\ascend-npus\\mindspore_backend.mdx", "source_location": "L156"}, {"id": "ascend_npus_mindspore_backend_codeblock_9", "label": "code:shell (export PROTOCOL_BUFFERS_PYTHON_IMPLEMENTATION=python  # to a)", "file_type": "document", "source_file": "D:\\transplant518test\\sglang518\\docs_new\\docs\\hardware-platforms\\ascend-npus\\mindspore_backend.mdx", "source_location": "L161"}, {"id": "ascend_npus_mindspore_backend_support", "label": "Support", "file_type": "document", "source_file": "D:\\transplant518test\\sglang518\\docs_new\\docs\\hardware-platforms\\ascend-npus\\mindspore_backend.mdx", "source_location": "L166"}], "edges": [{"source": "d_transplant518test_sglang518_docs_new_docs_hardware_platforms_ascend_npus_mindspore_backend_mdx", "target": "ascend_npus_mindspore_backend_introduction", "relation": "contains", "confidence": "EXTRACTED", "source_file": "D:\\transplant518test\\sglang518\\docs_new\\docs\\hardware-platforms\\ascend-npus\\mindspore_backend.mdx", "source_location": "L1", "weight": 1.0}, {"source": "d_transplant518test_sglang518_docs_new_docs_hardware_platforms_ascend_npus_mindspore_backend_mdx", "target": "ascend_npus_mindspore_backend_requirements", "relation": "contains", "confidence": "EXTRACTED", "source_file": "D:\\transplant518test\\sglang518\\docs_new\\docs\\hardware-platforms\\ascend-npus\\mindspore_backend.mdx", "source_location": "L5", "weight": 1.0}, {"source": "d_transplant518test_sglang518_docs_new_docs_hardware_platforms_ascend_npus_mindspore_backend_mdx", "target": "ascend_npus_mindspore_backend_supported_models", "relation": "contains", "confidence": "EXTRACTED", "source_file": "D:\\transplant518test\\sglang518\\docs_new\\docs\\hardware-platforms\\ascend-npus\\mindspore_backend.mdx", "source_location": "L10", "weight": 1.0}, {"source": "d_transplant518test_sglang518_docs_new_docs_hardware_platforms_ascend_npus_mindspore_backend_mdx", "target": "ascend_npus_mindspore_backend_installation", "relation": "contains", "confidence": "EXTRACTED", "source_file": "D:\\transplant518test\\sglang518\\docs_new\\docs\\hardware-platforms\\ascend-npus\\mindspore_backend.mdx", "source_location": "L18", "weight": 1.0}, {"source": "ascend_npus_mindspore_backend_installation", "target": "ascend_npus_mindspore_backend_codeblock_1", "relation": "contains", "confidence": "EXTRACTED", "source_file": "D:\\transplant518test\\sglang518\\docs_new\\docs\\hardware-platforms\\ascend-npus\\mindspore_backend.mdx", "source_location": "L25", "weight": 1.0}, {"source": "d_transplant518test_sglang518_docs_new_docs_hardware_platforms_ascend_npus_mindspore_backend_mdx", "target": "ascend_npus_mindspore_backend_run_model", "relation": "contains", "confidence": "EXTRACTED", "source_file": "D:\\transplant518test\\sglang518\\docs_new\\docs\\hardware-platforms\\ascend-npus\\mindspore_backend.mdx", "source_location": "L33", "weight": 1.0}, {"source": "ascend_npus_mindspore_backend_run_model", "target": "ascend_npus_mindspore_backend_offline_infer", "relation": "contains", "confidence": "EXTRACTED", "source_file": "D:\\transplant518test\\sglang518\\docs_new\\docs\\hardware-platforms\\ascend-npus\\mindspore_backend.mdx", "source_location": "L37", "weight": 1.0}, {"source": "ascend_npus_mindspore_backend_offline_infer", "target": "ascend_npus_mindspore_backend_codeblock_2", "relation": "contains", "confidence": "EXTRACTED", "source_file": "D:\\transplant518test\\sglang518\\docs_new\\docs\\hardware-platforms\\ascend-npus\\mindspore_backend.mdx", "source_location": "L42", "weight": 1.0}, {"source": "ascend_npus_mindspore_backend_run_model", "target": "ascend_npus_mindspore_backend_start_server", "relation": "contains", "confidence": "EXTRACTED", "source_file": "D:\\transplant518test\\sglang518\\docs_new\\docs\\hardware-platforms\\ascend-npus\\mindspore_backend.mdx", "source_location": "L72", "weight": 1.0}, {"source": "ascend_npus_mindspore_backend_start_server", "target": "ascend_npus_mindspore_backend_codeblock_3", "relation": "contains", "confidence": "EXTRACTED", "source_file": "D:\\transplant518test\\sglang518\\docs_new\\docs\\hardware-platforms\\ascend-npus\\mindspore_backend.mdx", "source_location": "L77", "weight": 1.0}, {"source": "ascend_npus_mindspore_backend_start_server", "target": "ascend_npus_mindspore_backend_codeblock_4", "relation": "contains", "confidence": "EXTRACTED", "source_file": "D:\\transplant518test\\sglang518\\docs_new\\docs\\hardware-platforms\\ascend-npus\\mindspore_backend.mdx", "source_location": "L93", "weight": 1.0}, {"source": "d_transplant518test_sglang518_docs_new_docs_hardware_platforms_ascend_npus_mindspore_backend_mdx", "target": "ascend_npus_mindspore_backend_troubleshooting", "relation": "contains", "confidence": "EXTRACTED", "source_file": "D:\\transplant518test\\sglang518\\docs_new\\docs\\hardware-platforms\\ascend-npus\\mindspore_backend.mdx", "source_location": "L109", "weight": 1.0}, {"source": "ascend_npus_mindspore_backend_troubleshooting", "target": "ascend_npus_mindspore_backend_debug_mode", "relation": "contains", "confidence": "EXTRACTED", "source_file": "D:\\transplant518test\\sglang518\\docs_new\\docs\\hardware-platforms\\ascend-npus\\mindspore_backend.mdx", "source_location": "L111", "weight": 1.0}, {"source": "ascend_npus_mindspore_backend_debug_mode", "target": "ascend_npus_mindspore_backend_codeblock_5", "relation": "contains", "confidence": "EXTRACTED", "source_file": "D:\\transplant518test\\sglang518\\docs_new\\docs\\hardware-platforms\\ascend-npus\\mindspore_backend.mdx", "source_location": "L116", "weight": 1.0}, {"source": "ascend_npus_mindspore_backend_debug_mode", "target": "ascend_npus_mindspore_backend_codeblock_6", "relation": "contains", "confidence": "EXTRACTED", "source_file": "D:\\transplant518test\\sglang518\\docs_new\\docs\\hardware-platforms\\ascend-npus\\mindspore_backend.mdx", "source_location": "L130", "weight": 1.0}, {"source": "ascend_npus_mindspore_backend_troubleshooting", "target": "ascend_npus_mindspore_backend_explicitly_select_devices", "relation": "contains", "confidence": "EXTRACTED", "source_file": "D:\\transplant518test\\sglang518\\docs_new\\docs\\hardware-platforms\\ascend-npus\\mindspore_backend.mdx", "source_location": "L136", "weight": 1.0}, {"source": "ascend_npus_mindspore_backend_explicitly_select_devices", "target": "ascend_npus_mindspore_backend_codeblock_7", "relation": "contains", "confidence": "EXTRACTED", "source_file": "D:\\transplant518test\\sglang518\\docs_new\\docs\\hardware-platforms\\ascend-npus\\mindspore_backend.mdx", "source_location": "L141", "weight": 1.0}, {"source": "ascend_npus_mindspore_backend_troubleshooting", "target": "ascend_npus_mindspore_backend_some_communication_environment_issues", "relation": "contains", "confidence": "EXTRACTED", "source_file": "D:\\transplant518test\\sglang518\\docs_new\\docs\\hardware-platforms\\ascend-npus\\mindspore_backend.mdx", "source_location": "L146", "weight": 1.0}, {"source": "ascend_npus_mindspore_backend_some_communication_environment_issues", "target": "ascend_npus_mindspore_backend_codeblock_8", "relation": "contains", "confidence": "EXTRACTED", "source_file": "D:\\transplant518test\\sglang518\\docs_new\\docs\\hardware-platforms\\ascend-npus\\mindspore_backend.mdx", "source_location": "L151", "weight": 1.0}, {"source": "ascend_npus_mindspore_backend_troubleshooting", "target": "ascend_npus_mindspore_backend_some_dependencies_of_protobuf", "relation": "contains", "confidence": "EXTRACTED", "source_file": "D:\\transplant518test\\sglang518\\docs_new\\docs\\hardware-platforms\\ascend-npus\\mindspore_backend.mdx", "source_location": "L156", "weight": 1.0}, {"source": "ascend_npus_mindspore_backend_some_dependencies_of_protobuf", "target": "ascend_npus_mindspore_backend_codeblock_9", "relation": "contains", "confidence": "EXTRACTED", "source_file": "D:\\transplant518test\\sglang518\\docs_new\\docs\\hardware-platforms\\ascend-npus\\mindspore_backend.mdx", "source_location": "L161", "weight": 1.0}, {"source": "d_transplant518test_sglang518_docs_new_docs_hardware_platforms_ascend_npus_mindspore_backend_mdx", "target": "ascend_npus_mindspore_backend_support", "relation": "contains", "confidence": "EXTRACTED", "source_file": "D:\\transplant518test\\sglang518\\docs_new\\docs\\hardware-platforms\\ascend-npus\\mindspore_backend.mdx", "source_location": "L166", "weight": 1.0}], "input_tokens": 0, "output_tokens": 0}